kv_to_kube/__init__.py
kv_to_kube-1.0.3.dist-info/LICENSE
kv_to_kube-1.0.3.dist-info/METADATA
kv_to_kube-1.0.3.dist-info/WHEEL
kv_to_kube-1.0.3.dist-info/entry_points.txt
kv_to_kube-1.0.3.dist-info/RECORD
