Metadata-Version: 2.1
Name: kv-to-kube
Version: 1.0.3
Summary: Sync Azure Key Vault Secrets to Kubernetes Secrets
License: MIT
Author: Chris Pressland
Author-email: mail@cpressland.io
Requires-Python: >=3.11,<4.0
Classifier: License :: OSI Approved :: MIT License
Classifier: Programming Language :: Python :: 3
Classifier: Programming Language :: Python :: 3.11
Classifier: Programming Language :: Python :: 3.12
Requires-Dist: azure-identity (>=1.14.1,<2.0.0)
Requires-Dist: azure-keyvault (>=4.2.0,<5.0.0)
Requires-Dist: click (>=8.1.7,<9.0.0)
Requires-Dist: kr8s (>=0.9.2,<0.10.0)
Requires-Dist: loguru (>=0.7.2,<0.8.0)
Requires-Dist: pydantic (>=2.4.2,<3.0.0)
